jupyternb/__init__.py
jupyternb/jupyter_startup.py
jupyternb_setup-1.3.7.dist-info/entry_points.txt
jupyternb_setup-1.3.7.dist-info/LICENSE
jupyternb_setup-1.3.7.dist-info/WHEEL
jupyternb_setup-1.3.7.dist-info/METADATA
jupyternb_setup-1.3.7.dist-info/RECORD
