Metadata-Version: 2.1
Name: jupyternb-setup
Version: 1.3.7
Summary: Fabric Jupyter Notebook Container Setup
Keywords: Fabric Jupyter Notebook Container Setup,Jupyter Hub,Jupyter Notebook
Author-email: Komal Thareja <kthare10@renci.org>
Requires-Python: >=3.9
Classifier: Programming Language :: Python :: 3
Classifier: License :: OSI Approved :: MIT License
Classifier: Operating System :: OS Independent
Requires-Dist: nbgitpuller
Requires-Dist: fabric_fss_utils
Requires-Dist: atomicwrites
Requires-Dist: gitpython
Requires-Dist: wget
Project-URL: Home, https://fabric-testbed.net/
Project-URL: Sources, https://github.com/fabric-testbed/jupyternb-setup
